gpm/__init__.py
gpm/_config.py
gpm/_version.py
gpm/checks.py
gpm/configs.py
gpm/accessor/__init__.py
gpm/accessor/methods.py
gpm/bucket/__init__.py
gpm/bucket/analysis.py
gpm/bucket/dataframe.py
gpm/bucket/filters.py
gpm/bucket/io.py
gpm/bucket/partitioning.py
gpm/bucket/readers.py
gpm/bucket/routines.py
gpm/bucket/writers.py
gpm/dataset/__init__.py
gpm/dataset/attrs.py
gpm/dataset/conventions.py
gpm/dataset/coords.py
gpm/dataset/crs.py
gpm/dataset/dataset.py
gpm/dataset/datatree.py
gpm/dataset/dimensions.py
gpm/dataset/granule.py
gpm/dataset/groups_variables.py
gpm/dataset/tcprimed.py
gpm/dataset/decoding/__init__.py
gpm/dataset/decoding/cf.py
gpm/dataset/decoding/coordinates.py
gpm/dataset/decoding/dataarray_attrs.py
gpm/dataset/decoding/decode_1b_radar.py
gpm/dataset/decoding/decode_1c_pmw.py
gpm/dataset/decoding/decode_2a_pmw.py
gpm/dataset/decoding/decode_2a_radar.py
gpm/dataset/decoding/decode_2b_corra.py
gpm/dataset/decoding/decode_imerg.py
gpm/dataset/decoding/routines.py
gpm/dataset/decoding/utils.py
gpm/encoding/__init__.py
gpm/encoding/encode_2a_radar.py
gpm/encoding/encode_imerg_v7.py
gpm/encoding/routines.py
gpm/etc/__init__.py
gpm/etc/products.yaml
gpm/etc/colorbars/1B_PMW_colorbars.yaml
gpm/etc/colorbars/1B_RADAR_colorbars.yaml
gpm/etc/colorbars/1C_PMW_colorbars.yaml
gpm/etc/colorbars/2A_DPR_colorbars.yaml
gpm/etc/colorbars/2A_PMW_colorbars.yaml
gpm/etc/colorbars/2A_SLH_colorbars.yaml
gpm/etc/colorbars/2B_CMB_colorbars.yaml
gpm/etc/colorbars/2B_CSH_colorbars.yaml
gpm/etc/colorbars/GV.yaml
gpm/etc/colorbars/IMERG_colorbars.yaml
gpm/etc/colorbars/TCPRIMED.yaml
gpm/etc/colorbars/climatology.yaml
gpm/etc/colorbars/default_colorbars.yaml
gpm/etc/colorbars/xradar.yaml
gpm/etc/colormaps/categorical/cat3_RdOrGr.yaml
gpm/etc/colormaps/categorical/surfaceTypeIndexPalette.yaml
gpm/etc/colormaps/precipitation/IMERG_Liquid.yaml
gpm/etc/colormaps/precipitation/IMERG_Solid.yaml
gpm/etc/colormaps/precipitation/MCH_Precip_Clim.yaml
gpm_api-0.3.4.dist-info/licenses/LICENSE
gpm_api-0.3.4.dist-info/METADATA
gpm_api-0.3.4.dist-info/WHEEL
gpm_api-0.3.4.dist-info/entry_points.txt
gpm_api-0.3.4.dist-info/top_level.txt
gpm_api-0.3.4.dist-info/RECORD
