Metadata-Version: 2.4
Name: gpm_api
Version: 0.3.4
Summary: Python Package for the Global Precipitation Measurement (GPM) Mission Data Archive
Author-email: Gionata Ghiggi <gionata.ghiggi@epfl.ch>
License: MIT License
Project-URL: homepage, https://github.com/ghiggi/gpm_api
Project-URL: repository, https://github.com/ghiggi/gpm_api
Project-URL: source, https://github.com/ghiggi/gpm_api
Project-URL: tracker, https://github.com/ghiggi/gpm_api/issues
Project-URL: documentation, https://gpm-api.readthedocs.io
Project-URL: changelog, https://github.com/ghiggi/gpm_api/blob/main/CHANGELOG.md
Keywords: GPM,Precipitation,API,DPR,PMW,IMERG
Classifier: Development Status :: 5 - Production/Stable
Classifier: Intended Audience :: Science/Research
Classifier: Intended Audience :: Education
Classifier: License :: OSI Approved :: MIT License
Classifier: Natural Language :: English
Classifier: Operating System :: OS Independent
Classifier: Operating System :: Unix
Classifier: Operating System :: Microsoft
Classifier: Operating System :: MacOS
Classifier: Programming Language :: Python
Classifier: Programming Language :: Python :: 3
Classifier: Programming Language :: Python :: 3 :: Only
Classifier: Programming Language :: Python :: 3.10
Classifier: Programming Language :: Python :: 3.11
Classifier: Programming Language :: Python :: 3.12
Classifier: Programming Language :: Python :: 3.13
Classifier: Topic :: Scientific/Engineering
Classifier: Topic :: Scientific/Engineering :: Atmospheric Science
Classifier: Topic :: Scientific/Engineering :: GIS
Classifier: Topic :: Scientific/Engineering :: Hydrology
Classifier: Topic :: Scientific/Engineering :: Image Processing
Requires-Python: >=3.10
License-File: LICENSE
Requires-Dist: xarray>=2025.01.0
Requires-Dist: xoak
Requires-Dist: netcdf4
Requires-Dist: dask
Requires-Dist: distributed
Requires-Dist: tqdm
Requires-Dist: click
Requires-Dist: pyyaml
Requires-Dist: donfig
Requires-Dist: trollsift
Requires-Dist: matplotlib>=3.8.3
Requires-Dist: cartopy>=0.22.0
Requires-Dist: pyproj
Requires-Dist: numpy
Requires-Dist: pandas
Requires-Dist: scipy
Requires-Dist: pycolorbar>=0.1.2
Provides-Extra: dev
Requires-Dist: pre-commit; extra == "dev"
Requires-Dist: loghub; extra == "dev"
Requires-Dist: black[jupyter]; extra == "dev"
Requires-Dist: blackdoc; extra == "dev"
Requires-Dist: codespell; extra == "dev"
Requires-Dist: ruff; extra == "dev"
Requires-Dist: pytest; extra == "dev"
Requires-Dist: pytest-cov; extra == "dev"
Requires-Dist: pytest-mock; extra == "dev"
Requires-Dist: pytest-check; extra == "dev"
Requires-Dist: pytest-sugar; extra == "dev"
Requires-Dist: pytest-watcher; extra == "dev"
Requires-Dist: deepdiff; extra == "dev"
Requires-Dist: pip-tools; extra == "dev"
Requires-Dist: bumpver; extra == "dev"
Requires-Dist: twine; extra == "dev"
Requires-Dist: wheel; extra == "dev"
Requires-Dist: build; extra == "dev"
Requires-Dist: setuptools>=61.0.0; extra == "dev"
Requires-Dist: ximage; extra == "dev"
Requires-Dist: pyvista; extra == "dev"
Requires-Dist: polars; extra == "dev"
Requires-Dist: pyarrow; extra == "dev"
Requires-Dist: pyresample; extra == "dev"
Requires-Dist: h5py; extra == "dev"
Requires-Dist: xoak; extra == "dev"
Requires-Dist: scikit-learn; extra == "dev"
Requires-Dist: sphinx; extra == "dev"
Requires-Dist: sphinx-gallery; extra == "dev"
Requires-Dist: sphinx-book-theme; extra == "dev"
Requires-Dist: nbsphinx; extra == "dev"
Requires-Dist: sphinx_mdinclude; extra == "dev"
Dynamic: license-file
